pulumi_render/__init__.py
pulumi_render/_utilities.py
pulumi_render/provider.py
pulumi_render/pulumi-plugin.json
pulumi_render/py.typed
pulumi_render/blueprints/__init__.py
pulumi_render/blueprints/_enums.py
pulumi_render/blueprints/get_blueprint.py
pulumi_render/blueprints/list_blueprint_syncs.py
pulumi_render/blueprints/list_blueprints.py
pulumi_render/blueprints/outputs.py
pulumi_render/config/__init__.py
pulumi_render/config/__init__.pyi
pulumi_render/config/vars.py
pulumi_render/cron_jobs/__init__.py
pulumi_render/cron_jobs/_enums.py
pulumi_render/cron_jobs/run_cron_job.py
pulumi_render/disks/__init__.py
pulumi_render/disks/disk.py
pulumi_render/disks/get_disk.py
pulumi_render/disks/list_disks.py
pulumi_render/disks/outputs.py
pulumi_render/disks/restore_snapshot.py
pulumi_render/env_groups/__init__.py
pulumi_render/env_groups/_enums.py
pulumi_render/env_groups/_inputs.py
pulumi_render/env_groups/env_group.py
pulumi_render/env_groups/env_group_env_var.py
pulumi_render/env_groups/env_group_secret_file.py
pulumi_render/env_groups/get_env_group.py
pulumi_render/env_groups/get_env_group_env_var.py
pulumi_render/env_groups/get_env_group_secret_file.py
pulumi_render/env_groups/link_service_to_env_group.py
pulumi_render/env_groups/list_env_groups.py
pulumi_render/env_groups/outputs.py
pulumi_render/environments/__init__.py
pulumi_render/environments/_enums.py
pulumi_render/environments/environment.py
pulumi_render/environments/get_environment.py
pulumi_render/environments/list_environments.py
pulumi_render/environments/outputs.py
pulumi_render/environments/resources_to_environment.py
pulumi_render/key_value/__init__.py
pulumi_render/key_value/_enums.py
pulumi_render/key_value/_inputs.py
pulumi_render/key_value/get_key_value.py
pulumi_render/key_value/get_key_value_connection_info.py
pulumi_render/key_value/key_value.py
pulumi_render/key_value/list_key_value.py
pulumi_render/key_value/outputs.py
pulumi_render/metrics/__init__.py
pulumi_render/metrics/_enums.py
pulumi_render-0.5.5.dist-info/METADATA
pulumi_render-0.5.5.dist-info/WHEEL
pulumi_render-0.5.5.dist-info/top_level.txt
pulumi_render-0.5.5.dist-info/RECORD
