Metadata-Version: 2.4
Name: pulumi_render
Version: 0.5.5
Summary: A Pulumi package for creating and managing Render resources.
License: Apache-2.0
Project-URL: Homepage, https://cloudysky.software
Project-URL: Repository, https://github.com/cloudy-sky-software/pulumi-render
Keywords: pulumi,render,category/cloud,kind/native
Requires-Python: >=3.9
Requires-Dist: parver>=0.2.1
Requires-Dist: pulumi<4.0.0,>=3.0.0
Requires-Dist: semver>=2.8.1
Requires-Dist: typing-extensions<5,>=4.11; python_version < "3.11"
